<?xml version="1.0" encoding="Windows-1252"?>
<GhostList xmlns:xsi="http://www.w3.org/2001/XMLSchema-instance" xmlns:xsd="http://www.w3.org/2001/XMLSchema">
  <_framePos>
    <Vector3>
      <x>0</x>
      <y>0</y>
      <z>0</z>
    </Vector3>
    <Vector3>
      <x>0</x>
      <y>0</y>
      <z>0</z>
    </Vector3>
    <Vector3>
      <x>0</x>
      <y>0.920000136</y>
      <z>0</z>
    </Vector3>
    <Vector3>
      <x>0</x>
      <y>1.88000023</y>
      <z>0</z>
    </Vector3>
    <Vector3>
      <x>0</x>
      <y>2.88</y>
      <z>0</z>
    </Vector3>
    <Vector3>
      <x>0</x>
      <y>3.9199996</y>
      <z>0</z>
    </Vector3>
    <Vector3>
      <x>0</x>
      <y>5</y>
      <z>0</z>
    </Vector3>
    <Vector3>
      <x>0</x>
      <y>6.12</y>
      <z>0</z>
    </Vector3>
    <Vector3>
      <x>0</x>
      <y>7.27999973</y>
      <z>0</z>
    </Vector3>
    <Vector3>
      <x>0</x>
      <y>8.48</y>
      <z>0</z>
    </Vector3>
    <Vector3>
      <x>0</x>
      <y>9.719999</y>
      <z>0</z>
    </Vector3>
    <Vector3>
      <x>0</x>
      <y>10.999999</y>
      <z>0</z>
    </Vector3>
    <Vector3>
      <x>359.985</x>
      <y>12.32</y>
      <z>-2.08440834E-10</z>
    </Vector3>
    <Vector3>
      <x>359.92984</x>
      <y>13.6799994</y>
      <z>-0.000356148928</z>
    </Vector3>
    <Vector3>
      <x>359.801636</x>
      <y>15.0800047</y>
      <z>-0.0020699848</z>
    </Vector3>
    <Vector3>
      <x>359.419739</x>
      <y>16.4217281</y>
      <z>359.9933</z>
    </Vector3>
    <Vector3>
      <x>358.977844</x>
      <y>17.74566</y>
      <z>359.9799</z>
    </Vector3>
    <Vector3>
      <x>358.418182</x>
      <y>19.0185146</y>
      <z>359.957184</z>
    </Vector3>
    <Vector3>
      <x>357.740082</x>
      <y>20.2197628</y>
      <z>359.924</z>
    </Vector3>
    <Vector3>
      <x>356.923981</x>
      <y>21.3266373</y>
      <z>359.880371</z>
    </Vector3>
    <Vector3>
      <x>355.698334</x>
      <y>22.1755428</y>
      <z>359.8348</z>
    </Vector3>
    <Vector3>
      <x>354.422333</x>
      <y>22.6360779</y>
      <z>359.800232</z>
    </Vector3>
    <Vector3>
      <x>352.983734</x>
      <y>23.0087986</y>
      <z>359.763916</z>
    </Vector3>
    <Vector3>
      <x>351.544159</x>
      <y>23.1129532</y>
      <z>359.751129</z>
    </Vector3>
    <Vector3>
      <x>350.1043</x>
      <y>23.15108</y>
      <z>359.745422</z>
    </Vector3>
    <Vector3>
      <x>348.6643</x>
      <y>23.1576</y>
      <z>359.744232</z>
    </Vector3>
    <Vector3>
      <x>347.224335</x>
      <y>23.16419</y>
      <z>359.742859</z>
    </Vector3>
    <Vector3>
      <x>345.784363</x>
      <y>23.1708565</y>
      <z>359.7413</z>
    </Vector3>
    <Vector3>
      <x>344.34436</x>
      <y>23.1776085</y>
      <z>359.739563</z>
    </Vector3>
    <Vector3>
      <x>342.9041</x>
      <y>23.120512</y>
      <z>359.754883</z>
    </Vector3>
    <Vector3>
      <x>341.463562</x>
      <y>22.9722462</y>
      <z>359.7984</z>
    </Vector3>
    <Vector3>
      <x>340.024567</x>
      <y>22.7123</y>
      <z>359.881</z>
    </Vector3>
    <Vector3>
      <x>338.6008</x>
      <y>22.3538589</y>
      <z>0.00347034866</z>
    </Vector3>
    <Vector3>
      <x>337.1881</x>
      <y>21.9260139</y>
      <z>0.1596231</z>
    </Vector3>
    <Vector3>
      <x>335.8027</x>
      <y>21.3809452</y>
      <z>0.371049047</z>
    </Vector3>
    <Vector3>
      <x>334.440979</x>
      <y>20.7671585</y>
      <z>0.622783661</z>
    </Vector3>
    <Vector3>
      <x>333.108551</x>
      <y>20.0714264</y>
      <z>0.9231601</z>
    </Vector3>
    <Vector3>
      <x>331.78363</x>
      <y>19.34225</y>
      <z>1.25324082</z>
    </Vector3>
    <Vector3>
      <x>330.468384</x>
      <y>18.582531</y>
      <z>1.612781</z>
    </Vector3>
    <Vector3>
      <x>329.1575</x>
      <y>17.80302</y>
      <z>1.99742246</z>
    </Vector3>
    <Vector3>
      <x>327.86026</x>
      <y>16.995512</y>
      <z>2.41190076</z>
    </Vector3>
    <Vector3>
      <x>326.5733</x>
      <y>16.1583347</y>
      <z>2.85782957</z>
    </Vector3>
    <Vector3>
      <x>325.292053</x>
      <y>15.2962141</y>
      <z>3.33338976</z>
    </Vector3>
    <Vector3>
      <x>324.016968</x>
      <y>14.4072323</y>
      <z>3.84030175</z>
    </Vector3>
    <Vector3>
      <x>322.748535</x>
      <y>13.48933</y>
      <z>4.38043451</z>
    </Vector3>
    <Vector3>
      <x>321.486145</x>
      <y>12.5584</y>
      <z>4.944866</z>
    </Vector3>
    <Vector3>
      <x>320.205872</x>
      <y>11.7144136</y>
      <z>5.47156858</z>
    </Vector3>
    <Vector3>
      <x>318.779266</x>
      <y>11.4416208</y>
      <z>5.647915</z>
    </Vector3>
    <Vector3>
      <x>317.3517</x>
      <y>11.1778622</y>
      <z>5.82353354</z>
    </Vector3>
    <Vector3>
      <x>315.919342</x>
      <y>10.9744883</y>
      <z>5.96318865</z>
    </Vector3>
    <Vector3>
      <x>314.4873</x>
      <y>10.7610245</y>
      <z>6.11360645</z>
    </Vector3>
    <Vector3>
      <x>313.027161</x>
      <y>10.9258413</y>
      <z>5.997914</z>
    </Vector3>
    <Vector3>
      <x>311.585358</x>
      <y>11.294282</y>
      <z>5.73025274</z>
    </Vector3>
    <Vector3>
      <x>310.157928</x>
      <y>11.7572289</y>
      <z>5.385495</z>
    </Vector3>
    <Vector3>
      <x>308.773163</x>
      <y>12.4046936</y>
      <z>4.8918643</z>
    </Vector3>
    <Vector3>
      <x>307.410675</x>
      <y>13.1702356</y>
      <z>4.29600143</z>
    </Vector3>
    <Vector3>
      <x>306.120422</x>
      <y>14.3037481</y>
      <z>3.39616227</z>
    </Vector3>
    <Vector3>
      <x>304.860168</x>
      <y>15.5870314</y>
      <z>2.359822</z>
    </Vector3>
    <Vector3>
      <x>303.6276</x>
      <y>17.00687</y>
      <z>1.19484246</z>
    </Vector3>
    <Vector3>
      <x>302.420959</x>
      <y>18.557354</y>
      <z>359.903717</z>
    </Vector3>
    <Vector3>
      <x>301.239777</x>
      <y>20.2369022</y>
      <z>358.4857</z>
    </Vector3>
    <Vector3>
      <x>300.085</x>
      <y>22.0004673</y>
      <z>356.977448</z>
    </Vector3>
    <Vector3>
      <x>298.937134</x>
      <y>23.8105373</y>
      <z>355.410645</z>
    </Vector3>
    <Vector3>
      <x>297.766266</x>
      <y>25.5807533</y>
      <z>353.860565</z>
    </Vector3>
    <Vector3>
      <x>296.528351</x>
      <y>27.1459274</y>
      <z>352.474152</z>
    </Vector3>
    <Vector3>
      <x>295.1753</x>
      <y>28.7609978</y>
      <z>351.026917</z>
    </Vector3>
    <Vector3>
      <x>293.753876</x>
      <y>29.31853</y>
      <z>350.5194</z>
    </Vector3>
    <Vector3>
      <x>292.334747</x>
      <y>29.9426174</y>
      <z>349.945068</z>
    </Vector3>
    <Vector3>
      <x>290.918274</x>
      <y>30.6467381</y>
      <z>349.290466</z>
    </Vector3>
    <Vector3>
      <x>289.505127</x>
      <y>31.4481182</y>
      <z>348.5384</z>
    </Vector3>
    <Vector3>
      <x>288.096</x>
      <y>32.369297</y>
      <z>347.6663</z>
    </Vector3>
    <Vector3>
      <x>286.692</x>
      <y>33.4401436</y>
      <z>346.644318</z>
    </Vector3>
    <Vector3>
      <x>285.294434</x>
      <y>34.7011452</y>
      <z>345.432037</z>
    </Vector3>
    <Vector3>
      <x>283.8835</x>
      <y>35.8882751</y>
      <z>344.282074</z>
    </Vector3>
    <Vector3>
      <x>282.450073</x>
      <y>36.888443</y>
      <z>343.305847</z>
    </Vector3>
    <Vector3>
      <x>281.039063</x>
      <y>37.5023727</y>
      <z>342.7012</z>
    </Vector3>
    <Vector3>
      <x>279.6305</x>
      <y>36.697506</y>
      <z>343.486816</z>
    </Vector3>
    <Vector3>
      <x>278.255737</x>
      <y>34.5807724</y>
      <z>345.5706</z>
    </Vector3>
    <Vector3>
      <x>276.960754</x>
      <y>30.5377426</y>
      <z>349.570282</z>
    </Vector3>
    <Vector3>
      <x>275.812225</x>
      <y>23.5575352</y>
      <z>356.499329</z>
    </Vector3>
    <Vector3>
      <x>275.0079</x>
      <y>11.535429</y>
      <z>8.460466</z>
    </Vector3>
    <Vector3>
      <x>274.6128</x>
      <y>355.492065</y>
      <z>24.44041</z>
    </Vector3>
    <Vector3>
      <x>274.737427</x>
      <y>338.3434</y>
      <z>41.5257874</z>
    </Vector3>
    <Vector3>
      <x>275.340118</x>
      <y>323.917145</y>
      <z>55.8908768</z>
    </Vector3>
    <Vector3>
      <x>276.282532</x>
      <y>313.764435</y>
      <z>65.9869461</z>
    </Vector3>
    <Vector3>
      <x>277.479218</x>
      <y>307.698883</y>
      <z>72.0062</z>
    </Vector3>
    <Vector3>
      <x>278.77475</x>
      <y>303.793579</y>
      <z>75.87047</z>
    </Vector3>
    <Vector3>
      <x>280.1247</x>
      <y>301.192963</y>
      <z>78.4345551</z>
    </Vector3>
    <Vector3>
      <x>281.52594</x>
      <y>299.426422</y>
      <z>80.16896</z>
    </Vector3>
    <Vector3>
      <x>282.940155</x>
      <y>298.124939</y>
      <z>81.44039</z>
    </Vector3>
    <Vector3>
      <x>284.3622</x>
      <y>297.1565</y>
      <z>82.38123</z>
    </Vector3>
    <Vector3>
      <x>285.785858</x>
      <y>296.3601</y>
      <z>83.14997</z>
    </Vector3>
    <Vector3>
      <x>287.1753</x>
      <y>295.459381</y>
      <z>84.0125351</z>
    </Vector3>
    <Vector3>
      <x>288.445862</x>
      <y>293.294128</y>
      <z>86.06782</z>
    </Vector3>
    <Vector3>
      <x>289.166229</x>
      <y>289.930725</y>
      <z>89.24479</z>
    </Vector3>
    <Vector3>
      <x>289.454529</x>
      <y>285.59375</y>
      <z>93.3347855</z>
    </Vector3>
    <Vector3>
      <x>289.589081</x>
      <y>281.302429</y>
      <z>97.37962</z>
    </Vector3>
    <Vector3>
      <x>289.742279</x>
      <y>277.039734</y>
      <z>101.394936</z>
    </Vector3>
    <Vector3>
      <x>289.92627</x>
      <y>272.8053</y>
      <z>105.38031</z>
    </Vector3>
    <Vector3>
      <x>290.118469</x>
      <y>268.573242</y>
      <z>109.359955</z>
    </Vector3>
    <Vector3>
      <x>290.181152</x>
      <y>264.4003</y>
      <z>113.283211</z>
    </Vector3>
    <Vector3>
      <x>290.2458</x>
      <y>260.23764</y>
      <z>117.196114</z>
    </Vector3>
    <Vector3>
      <x>290.304382</x>
      <y>256.088867</y>
      <z>121.095291</z>
    </Vector3>
    <Vector3>
      <x>290.436676</x>
      <y>251.9711</y>
      <z>124.963226</z>
    </Vector3>
    <Vector3>
      <x>290.629669</x>
      <y>247.897385</y>
      <z>128.786041</z>
    </Vector3>
    <Vector3>
      <x>290.872925</x>
      <y>243.864319</y>
      <z>132.565781</z>
    </Vector3>
    <Vector3>
      <x>291.1999</x>
      <y>239.929</y>
      <z>136.247147</z>
    </Vector3>
    <Vector3>
      <x>291.612183</x>
      <y>236.112946</y>
      <z>139.8084</z>
    </Vector3>
    <Vector3>
      <x>292.105469</x>
      <y>232.4525</y>
      <z>143.214035</z>
    </Vector3>
    <Vector3>
      <x>292.687225</x>
      <y>228.996155</y>
      <z>146.417831</z>
    </Vector3>
    <Vector3>
      <x>293.7509</x>
      <y>226.429718</y>
      <z>148.780136</z>
    </Vector3>
    <Vector3>
      <x>294.992828</x>
      <y>224.66304</y>
      <z>150.389481</z>
    </Vector3>
    <Vector3>
      <x>296.277557</x>
      <y>223.154587</y>
      <z>151.748917</z>
    </Vector3>
    <Vector3>
      <x>297.7131</x>
      <y>222.745087</y>
      <z>152.107788</z>
    </Vector3>
    <Vector3>
      <x>299.1559</x>
      <y>222.7975</y>
      <z>152.054016</z>
    </Vector3>
    <Vector3>
      <x>300.586761</x>
      <y>223.104126</y>
      <z>151.7797</z>
    </Vector3>
    <Vector3>
      <x>301.974548</x>
      <y>223.661423</y>
      <z>151.294724</z>
    </Vector3>
    <Vector3>
      <x>303.312866</x>
      <y>224.433014</y>
      <z>150.636414</z>
    </Vector3>
    <Vector3>
      <x>304.6096</x>
      <y>225.3757</y>
      <z>149.846176</z>
    </Vector3>
    <Vector3>
      <x>305.8264</x>
      <y>226.6046</y>
      <z>148.834778</z>
    </Vector3>
    <Vector3>
      <x>307.0123</x>
      <y>227.886124</y>
      <z>147.796722</z>
    </Vector3>
    <Vector3>
      <x>308.143524</x>
      <y>229.2641</y>
      <z>146.698853</z>
    </Vector3>
    <Vector3>
      <x>309.26828</x>
      <y>230.620682</y>
      <z>145.634781</z>
    </Vector3>
    <Vector3>
      <x>310.3585</x>
      <y>232.010422</y>
      <z>144.562668</z>
    </Vector3>
    <Vector3>
      <x>311.397369</x>
      <y>233.473785</y>
      <z>143.452789</z>
    </Vector3>
    <Vector3>
      <x>312.434448</x>
      <y>234.909424</y>
      <z>142.3814</z>
    </Vector3>
    <Vector3>
      <x>313.478729</x>
      <y>236.313354</y>
      <z>141.351028</z>
    </Vector3>
    <Vector3>
      <x>314.533142</x>
      <y>237.6806</y>
      <z>140.364868</z>
    </Vector3>
    <Vector3>
      <x>315.592773</x>
      <y>238.996323</y>
      <z>139.4329</z>
    </Vector3>
    <Vector3>
      <x>316.684265</x>
      <y>240.133453</y>
      <z>138.641586</z>
    </Vector3>
    <Vector3>
      <x>317.8199</x>
      <y>241.048645</y>
      <z>138.015945</z>
    </Vector3>
    <Vector3>
      <x>318.995239</x>
      <y>241.7373</y>
      <z>137.5534</z>
    </Vector3>
    <Vector3>
      <x>320.209534</x>
      <y>242.20755</y>
      <z>137.242432</z>
    </Vector3>
    <Vector3>
      <x>321.631348</x>
      <y>242.191574</y>
      <z>137.243744</z>
    </Vector3>
    <Vector3>
      <x>322.786621</x>
      <y>241.592865</y>
      <z>137.606216</z>
    </Vector3>
    <Vector3>
      <x>323.960632</x>
      <y>240.903992</y>
      <z>138.013092</z>
    </Vector3>
    <Vector3>
      <x>325.212463</x>
      <y>239.971741</y>
      <z>138.550018</z>
    </Vector3>
    <Vector3>
      <x>326.2972</x>
      <y>238.825989</y>
      <z>139.194824</z>
    </Vector3>
    <Vector3>
      <x>327.392242</x>
      <y>237.708923</y>
      <z>139.805786</z>
    </Vector3>
    <Vector3>
      <x>328.454926</x>
      <y>236.559448</y>
      <z>140.4171</z>
    </Vector3>
    <Vector3>
      <x>329.478638</x>
      <y>235.365662</y>
      <z>141.034378</z>
    </Vector3>
    <Vector3>
      <x>330.470581</x>
      <y>234.135284</y>
      <z>141.652756</z>
    </Vector3>
    <Vector3>
      <x>331.4327</x>
      <y>232.868713</y>
      <z>142.271286</z>
    </Vector3>
    <Vector3>
      <x>332.338</x>
      <y>231.567612</y>
      <z>142.888916</z>
    </Vector3>
    <Vector3>
      <x>333.12674</x>
      <y>230.17659</y>
      <z>143.532455</z>
    </Vector3>
    <Vector3>
      <x>333.8163</x>
      <y>228.740952</y>
      <z>144.180939</z>
    </Vector3>
    <Vector3>
      <x>334.455475</x>
      <y>227.281662</y>
      <z>144.8254</z>
    </Vector3>
    <Vector3>
      <x>335.0798</x>
      <y>225.8174</y>
      <z>145.4577</z>
    </Vector3>
    <Vector3>
      <x>335.6693</x>
      <y>224.333252</y>
      <z>146.0847</z>
    </Vector3>
    <Vector3>
      <x>336.2119</x>
      <y>222.822083</y>
      <z>146.709808</z>
    </Vector3>
    <Vector3>
      <x>336.754333</x>
      <y>221.314011</y>
      <z>147.320724</z>
    </Vector3>
    <Vector3>
      <x>337.2988</x>
      <y>219.807663</y>
      <z>147.917923</z>
    </Vector3>
    <Vector3>
      <x>337.851</x>
      <y>218.3104</y>
      <z>148.498383</z>
    </Vector3>
    <Vector3>
      <x>338.4396</x>
      <y>216.851746</y>
      <z>149.050369</z>
    </Vector3>
    <Vector3>
      <x>339.205444</x>
      <y>215.535065</y>
      <z>149.533524</z>
    </Vector3>
    <Vector3>
      <x>340.369263</x>
      <y>214.615936</y>
      <z>149.853088</z>
    </Vector3>
    <Vector3>
      <x>341.6161</x>
      <y>213.853928</y>
      <z>150.101288</z>
    </Vector3>
    <Vector3>
      <x>342.865875</x>
      <y>213.102844</y>
      <z>150.330383</z>
    </Vector3>
    <Vector3>
      <x>344.245819</x>
      <y>212.638779</y>
      <z>150.458115</z>
    </Vector3>
    <Vector3>
      <x>345.655182</x>
      <y>212.288773</y>
      <z>150.544144</z>
    </Vector3>
    <Vector3>
      <x>347.239227</x>
      <y>212.420074</y>
      <z>150.503143</z>
    </Vector3>
    <Vector3>
      <x>348.8234</x>
      <y>212.549438</y>
      <z>150.46608</z>
    </Vector3>
    <Vector3>
      <x>350.246338</x>
      <y>212.922485</y>
      <z>150.3889</z>
    </Vector3>
    <Vector3>
      <x>351.527985</x>
      <y>213.557648</y>
      <z>150.280029</z>
    </Vector3>
    <Vector3>
      <x>352.773163</x>
      <y>214.245773</y>
      <z>150.1782</z>
    </Vector3>
    <Vector3>
      <x>353.943939</x>
      <y>215.036331</y>
      <z>150.07988</z>
    </Vector3>
    <Vector3>
      <x>355.043152</x>
      <y>215.915558</y>
      <z>149.989624</z>
    </Vector3>
    <Vector3>
      <x>356.065338</x>
      <y>216.880249</y>
      <z>149.91011</z>
    </Vector3>
    <Vector3>
      <x>356.96582</x>
      <y>218.024689</y>
      <z>149.837967</z>
    </Vector3>
    <Vector3>
      <x>357.823669</x>
      <y>219.1928</y>
      <z>149.782928</z>
    </Vector3>
    <Vector3>
      <x>358.6524</x>
      <y>220.37709</y>
      <z>149.74501</z>
    </Vector3>
    <Vector3>
      <x>359.463</x>
      <y>221.571457</y>
      <z>149.724121</z>
    </Vector3>
    <Vector3>
      <x>0.267213345</x>
      <y>222.769424</y>
      <z>149.720184</z>
    </Vector3>
    <Vector3>
      <x>1.08144546</x>
      <y>223.8813</y>
      <z>149.731552</z>
    </Vector3>
    <Vector3>
      <x>2.29550982</x>
      <y>224.697464</y>
      <z>149.748276</z>
    </Vector3>
    <Vector3>
      <x>3.51907063</x>
      <y>225.394135</y>
      <z>149.776123</z>
    </Vector3>
    <Vector3>
      <x>4.94347954</x>
      <y>225.418213</y>
      <z>149.770035</z>
    </Vector3>
    <Vector3>
      <x>6.346183</x>
      <y>224.962784</y>
      <z>149.721283</z>
    </Vector3>
    <Vector3>
      <x>7.55221176</x>
      <y>224.166718</y>
      <z>149.625885</z>
    </Vector3>
    <Vector3>
      <x>8.709601</x>
      <y>223.2851</y>
      <z>149.503265</z>
    </Vector3>
    <Vector3>
      <x>9.742428</x>
      <y>222.312576</y>
      <z>149.350952</z>
    </Vector3>
    <Vector3>
      <x>10.5152512</x>
      <y>220.959564</y>
      <z>149.1218</z>
    </Vector3>
    <Vector3>
      <x>11.1605053</x>
      <y>219.5746</y>
      <z>148.870483</z>
    </Vector3>
    <Vector3>
      <x>11.6902</x>
      <y>218.18</y>
      <z>148.603271</z>
    </Vector3>
    <Vector3>
      <x>12.15731</x>
      <y>216.777557</y>
      <z>148.32251</z>
    </Vector3>
    <Vector3>
      <x>12.5789633</x>
      <y>215.3685</y>
      <z>148.029633</z>
    </Vector3>
    <Vector3>
      <x>12.9795237</x>
      <y>213.953949</y>
      <z>147.725677</z>
    </Vector3>
    <Vector3>
      <x>13.3422785</x>
      <y>212.537186</y>
      <z>147.411942</z>
    </Vector3>
    <Vector3>
      <x>13.7122164</x>
      <y>211.112823</y>
      <z>147.087677</z>
    </Vector3>
    <Vector3>
      <x>14.38519</x>
      <y>210.003983</y>
      <z>146.823868</z>
    </Vector3>
    <Vector3>
      <x>15.5890226</x>
      <y>209.185959</y>
      <z>146.6123</z>
    </Vector3>
    <Vector3>
      <x>16.7897968</x>
      <y>208.358276</y>
      <z>146.381531</z>
    </Vector3>
    <Vector3>
      <x>18.2154274</x>
      <y>207.957169</y>
      <z>146.255112</z>
    </Vector3>
    <Vector3>
      <x>19.67266</x>
      <y>207.761154</y>
      <z>146.18396</z>
    </Vector3>
    <Vector3>
      <x>21.1303349</x>
      <y>207.6461</y>
      <z>146.135834</z>
    </Vector3>
    <Vector3>
      <x>22.5589256</x>
      <y>207.707809</y>
      <z>146.1503</z>
    </Vector3>
    <Vector3>
      <x>23.9495659</x>
      <y>207.944672</y>
      <z>146.2352</z>
    </Vector3>
    <Vector3>
      <x>25.2687378</x>
      <y>208.4761</y>
      <z>146.4483</z>
    </Vector3>
    <Vector3>
      <x>26.550663</x>
      <y>209.13298</y>
      <z>146.727554</z>
    </Vector3>
    <Vector3>
      <x>27.7841225</x>
      <y>209.902267</y>
      <z>147.071671</z>
    </Vector3>
    <Vector3>
      <x>28.9687176</x>
      <y>210.7728</y>
      <z>147.478882</z>
    </Vector3>
    <Vector3>
      <x>30.1008625</x>
      <y>211.7408</y>
      <z>147.950256</z>
    </Vector3>
    <Vector3>
      <x>31.1520729</x>
      <y>212.839279</y>
      <z>148.505219</z>
    </Vector3>
    <Vector3>
      <x>32.16883</x>
      <y>213.996353</y>
      <z>149.1083</z>
    </Vector3>
    <Vector3>
      <x>33.1579323</x>
      <y>215.201263</y>
      <z>149.7546</z>
    </Vector3>
    <Vector3>
      <x>34.12476</x>
      <y>216.4482</y>
      <z>150.441559</z>
    </Vector3>
    <Vector3>
      <x>35.06948</x>
      <y>217.729965</y>
      <z>151.165649</z>
    </Vector3>
    <Vector3>
      <x>35.99364</x>
      <y>219.0471</y>
      <z>151.927521</z>
    </Vector3>
    <Vector3>
      <x>36.9395676</x>
      <y>220.271652</y>
      <z>152.651031</z>
    </Vector3>
    <Vector3>
      <x>38.2755356</x>
      <y>221.122177</y>
      <z>153.1608</z>
    </Vector3>
    <Vector3>
      <x>39.6052666</x>
      <y>222.004242</y>
      <z>153.705917</z>
    </Vector3>
    <Vector3>
      <x>40.8286972</x>
      <y>222.17627</y>
      <z>153.81102</z>
    </Vector3>
    <Vector3>
      <x>42.11774</x>
      <y>221.319565</y>
      <z>153.243622</z>
    </Vector3>
    <Vector3>
      <x>43.26291</x>
      <y>220.0647</y>
      <z>152.396454</z>
    </Vector3>
    <Vector3>
      <x>44.3292</x>
      <y>218.663223</y>
      <z>151.431259</z>
    </Vector3>
    <Vector3>
      <x>45.3087921</x>
      <y>217.1245</y>
      <z>150.352371</z>
    </Vector3>
    <Vector3>
      <x>46.19147</x>
      <y>215.45076</y>
      <z>149.160034</z>
    </Vector3>
    <Vector3>
      <x>46.91587</x>
      <y>213.6041</y>
      <z>147.827118</z>
    </Vector3>
    <Vector3>
      <x>47.5561447</x>
      <y>211.659286</y>
      <z>146.407578</z>
    </Vector3>
    <Vector3>
      <x>48.15164</x>
      <y>209.65712</y>
      <z>144.931442</z>
    </Vector3>
    <Vector3>
      <x>48.6948</x>
      <y>207.5947</y>
      <z>143.39711</z>
    </Vector3>
    <Vector3>
      <x>49.18348</x>
      <y>205.47789</y>
      <z>141.809586</z>
    </Vector3>
    <Vector3>
      <x>49.63508</x>
      <y>203.324661</y>
      <z>140.183044</z>
    </Vector3>
    <Vector3>
      <x>50.0610352</x>
      <y>201.159134</y>
      <z>138.536179</z>
    </Vector3>
    <Vector3>
      <x>50.5220337</x>
      <y>198.997849</y>
      <z>136.881287</z>
    </Vector3>
    <Vector3>
      <x>51.3907547</x>
      <y>197.133362</y>
      <z>135.436172</z>
    </Vector3>
    <Vector3>
      <x>52.4576759</x>
      <y>195.560547</y>
      <z>134.197067</z>
    </Vector3>
    <Vector3>
      <x>53.57772</x>
      <y>194.027847</y>
      <z>132.970444</z>
    </Vector3>
    <Vector3>
      <x>54.96624</x>
      <y>192.978561</y>
      <z>132.111145</z>
    </Vector3>
    <Vector3>
      <x>56.38572</x>
      <y>192.168869</y>
      <z>131.433929</z>
    </Vector3>
    <Vector3>
      <x>57.8068275</x>
      <y>191.58783</y>
      <z>130.937241</z>
    </Vector3>
    <Vector3>
      <x>59.222435</x>
      <y>191.581619</y>
      <z>130.9233</z>
    </Vector3>
    <Vector3>
      <x>60.6329231</x>
      <y>191.848846</y>
      <z>131.146271</z>
    </Vector3>
    <Vector3>
      <x>62.0275459</x>
      <y>192.382568</y>
      <z>131.606842</z>
    </Vector3>
    <Vector3>
      <x>63.38348</x>
      <y>193.2697</y>
      <z>132.388519</z>
    </Vector3>
    <Vector3>
      <x>64.72275</x>
      <y>194.329071</y>
      <z>133.334717</z>
    </Vector3>
    <Vector3>
      <x>66.0066147</x>
      <y>195.786072</y>
      <z>134.653854</z>
    </Vector3>
    <Vector3>
      <x>67.26114</x>
      <y>197.4796</y>
      <z>136.2036</z>
    </Vector3>
    <Vector3>
      <x>68.483696</x>
      <y>199.407059</y>
      <z>137.984436</z>
    </Vector3>
    <Vector3>
      <x>69.67589</x>
      <y>201.595459</y>
      <z>140.024078</z>
    </Vector3>
    <Vector3>
      <x>70.83302</x>
      <y>204.0715</y>
      <z>142.350174</z>
    </Vector3>
    <Vector3>
      <x>71.93854</x>
      <y>206.811768</y>
      <z>144.942856</z>
    </Vector3>
    <Vector3>
      <x>73.01984</x>
      <y>209.574677</y>
      <z>147.57283</z>
    </Vector3>
    <Vector3>
      <x>74.08605</x>
      <y>212.443161</y>
      <z>150.31871</z>
    </Vector3>
    <Vector3>
      <x>75.42742</x>
      <y>214.543152</y>
      <z>152.336014</z>
    </Vector3>
    <Vector3>
      <x>76.79875</x>
      <y>212.484818</y>
      <z>150.334885</z>
    </Vector3>
    <Vector3>
      <x>77.90097</x>
      <y>208.1175</y>
      <z>146.076172</z>
    </Vector3>
    <Vector3>
      <x>78.88811</x>
      <y>202.708633</y>
      <z>140.781143</z>
    </Vector3>
    <Vector3>
      <x>79.70929</x>
      <y>196.043991</y>
      <z>134.236481</z>
    </Vector3>
    <Vector3>
      <x>80.3036652</x>
      <y>188.190186</y>
      <z>126.506714</z>
    </Vector3>
    <Vector3>
      <x>80.63848</x>
      <y>179.437546</y>
      <z>117.880325</z>
    </Vector3>
    <Vector3>
      <x>80.60824</x>
      <y>170.387924</y>
      <z>108.958305</z>
    </Vector3>
    <Vector3>
      <x>80.27947</x>
      <y>161.7519</y>
      <z>100.449394</z>
    </Vector3>
    <Vector3>
      <x>79.69819</x>
      <y>153.969223</y>
      <z>92.7929</z>
    </Vector3>
    <Vector3>
      <x>78.91678</x>
      <y>147.221024</y>
      <z>86.16989</z>
    </Vector3>
    <Vector3>
      <x>77.98228</x>
      <y>141.494019</y>
      <z>80.5671539</z>
    </Vector3>
    <Vector3>
      <x>76.9229355</x>
      <y>136.705536</y>
      <z>75.90158</z>
    </Vector3>
    <Vector3>
      <x>75.7997055</x>
      <y>132.630432</y>
      <z>71.94985</z>
    </Vector3>
    <Vector3>
      <x>74.96753</x>
      <y>127.766174</y>
      <z>67.24712</z>
    </Vector3>
    <Vector3>
      <x>74.35542</x>
      <y>122.836281</y>
      <z>62.4925652</z>
    </Vector3>
    <Vector3>
      <x>73.6932755</x>
      <y>118.182816</y>
      <z>58.0178146</z>
    </Vector3>
    <Vector3>
      <x>73.04077</x>
      <y>113.647812</y>
      <z>53.6699181</z>
    </Vector3>
    <Vector3>
      <x>72.6543045</x>
      <y>108.565422</y>
      <z>48.8054161</z>
    </Vector3>
    <Vector3>
      <x>72.2238846</x>
      <y>103.722855</y>
      <z>44.1800423</z>
    </Vector3>
    <Vector3>
      <x>71.77985</x>
      <y>99.04096</y>
      <z>39.71817</z>
    </Vector3>
    <Vector3>
      <x>71.43446</x>
      <y>94.530014</y>
      <z>35.4282722</z>
    </Vector3>
    <Vector3>
      <x>71.10725</x>
      <y>90.1521454</y>
      <z>31.27294</z>
    </Vector3>
    <Vector3>
      <x>70.71983</x>
      <y>85.92242</y>
      <z>27.2665138</z>
    </Vector3>
    <Vector3>
      <x>70.31647</x>
      <y>81.82361</y>
      <z>23.3933678</z>
    </Vector3>
    <Vector3>
      <x>69.853714</x>
      <y>77.87467</y>
      <z>19.6716537</z>
    </Vector3>
    <Vector3>
      <x>69.33764</x>
      <y>74.0806351</y>
      <z>16.1068745</z>
    </Vector3>
    <Vector3>
      <x>68.7475052</x>
      <y>70.46551</y>
      <z>12.722086</z>
    </Vector3>
    <Vector3>
      <x>68.09296</x>
      <y>67.05221</y>
      <z>9.539338</z>
    </Vector3>
    <Vector3>
      <x>67.37112</x>
      <y>63.85369</y>
      <z>6.57071829</z>
    </Vector3>
    <Vector3>
      <x>66.5880356</x>
      <y>60.90589</y>
      <z>3.849187</z>
    </Vector3>
    <Vector3>
      <x>65.75188</x>
      <y>58.25454</y>
      <z>1.415778</z>
    </Vector3>
    <Vector3>
      <x>64.8727646</x>
      <y>55.8123055</y>
      <z>359.1888</z>
    </Vector3>
    <Vector3>
      <x>63.95699</x>
      <y>53.5695953</y>
      <z>357.1582</z>
    </Vector3>
    <Vector3>
      <x>62.9754372</x>
      <y>51.5317955</y>
      <z>355.327118</z>
    </Vector3>
    <Vector3>
      <x>61.92808</x>
      <y>49.710968</y>
      <z>353.704773</z>
    </Vector3>
    <Vector3>
      <x>60.7805977</x>
      <y>48.2235031</y>
      <z>352.3915</z>
    </Vector3>
    <Vector3>
      <x>59.58116</x>
      <y>46.93689</y>
      <z>351.267456</z>
    </Vector3>
    <Vector3>
      <x>58.34024</x>
      <y>45.8325539</y>
      <z>350.31366</z>
    </Vector3>
    <Vector3>
      <x>57.05687</x>
      <y>44.95296</y>
      <z>349.563049</z>
    </Vector3>
    <Vector3>
      <x>55.7553139</x>
      <y>44.1850357</y>
      <z>348.916443</z>
    </Vector3>
    <Vector3>
      <x>54.407444</x>
      <y>43.64595</y>
      <z>348.46814</z>
    </Vector3>
    <Vector3>
      <x>53.04877</x>
      <y>43.17162</y>
      <z>348.079559</z>
    </Vector3>
    <Vector3>
      <x>51.68235</x>
      <y>42.7453156</y>
      <z>347.7359</z>
    </Vector3>
    <Vector3>
      <x>50.3072624</x>
      <y>42.3317642</y>
      <z>347.408325</z>
    </Vector3>
    <Vector3>
      <x>48.92689</x>
      <y>41.915947</y>
      <z>347.0852</z>
    </Vector3>
    <Vector3>
      <x>47.5478439</x>
      <y>41.3943024</y>
      <z>346.688873</z>
    </Vector3>
    <Vector3>
      <x>46.17348</x>
      <y>40.79045</y>
      <z>346.2404</z>
    </Vector3>
    <Vector3>
      <x>44.7991028</x>
      <y>40.15105</y>
      <z>345.7762</z>
    </Vector3>
    <Vector3>
      <x>43.422924</x>
      <y>39.4943123</y>
      <z>345.310577</z>
    </Vector3>
    <Vector3>
      <x>42.0414352</x>
      <y>38.8381844</y>
      <z>344.856628</z>
    </Vector3>
    <Vector3>
      <x>40.6584167</x>
      <y>38.174202</y>
      <z>344.409027</z>
    </Vector3>
    <Vector3>
      <x>39.2750549</x>
      <y>37.53625</y>
      <z>343.990356</z>
    </Vector3>
    <Vector3>
      <x>37.8864059</x>
      <y>36.9153</y>
      <z>343.594177</z>
    </Vector3>
    <Vector3>
      <x>36.494545</x>
      <y>36.31763</y>
      <z>343.223938</z>
    </Vector3>
    <Vector3>
      <x>35.09731</x>
      <y>35.7317352</y>
      <z>342.872223</z>
    </Vector3>
    <Vector3>
      <x>33.7184753</x>
      <y>35.09286</y>
      <z>342.501923</z>
    </Vector3>
    <Vector3>
      <x>32.362072</x>
      <y>34.4325676</y>
      <z>342.13266</z>
    </Vector3>
    <Vector3>
      <x>31.0268517</x>
      <y>33.7579346</y>
      <z>341.769073</z>
    </Vector3>
    <Vector3>
      <x>29.70659</x>
      <y>33.0773354</y>
      <z>341.4159</z>
    </Vector3>
    <Vector3>
      <x>28.4049931</x>
      <y>32.39257</y>
      <z>341.074371</z>
    </Vector3>
    <Vector3>
      <x>27.107172</x>
      <y>31.71401</y>
      <z>340.74942</z>
    </Vector3>
    <Vector3>
      <x>25.80608</x>
      <y>31.0512486</y>
      <z>340.4452</z>
    </Vector3>
    <Vector3>
      <x>24.5065041</x>
      <y>30.401329</y>
      <z>340.160034</z>
    </Vector3>
    <Vector3>
      <x>23.2061443</x>
      <y>29.8177757</y>
      <z>339.9154</z>
    </Vector3>
    <Vector3>
      <x>21.8652744</x>
      <y>29.4373035</y>
      <z>339.761719</z>
    </Vector3>
    <Vector3>
      <x>20.5118618</x>
      <y>29.1553535</y>
      <z>339.652466</z>
    </Vector3>
    <Vector3>
      <x>19.1432018</x>
      <y>28.9851685</y>
      <z>339.588</z>
    </Vector3>
    <Vector3>
      <x>17.7649612</x>
      <y>28.92997</y>
      <z>339.564636</z>
    </Vector3>
    <Vector3>
      <x>16.2685432</x>
      <y>29.0427227</y>
      <z>339.592346</z>
    </Vector3>
    <Vector3>
      <x>14.9183016</x>
      <y>29.562315</y>
      <z>339.732025</z>
    </Vector3>
    <Vector3>
      <x>13.5669041</x>
      <y>30.07542</y>
      <z>339.858276</z>
    </Vector3>
    <Vector3>
      <x>12.3272467</x>
      <y>30.8999615</y>
      <z>340.04718</z>
    </Vector3>
    <Vector3>
      <x>11.1272087</x>
      <y>31.7902317</y>
      <z>340.233276</z>
    </Vector3>
    <Vector3>
      <x>10.1318283</x>
      <y>33.1032829</y>
      <z>340.486023</z>
    </Vector3>
    <Vector3>
      <x>9.32782</x>
      <y>34.4346924</y>
      <z>340.7212</z>
    </Vector3>
    <Vector3>
      <x>8.672082</x>
      <y>35.7985878</y>
      <z>340.944336</z>
    </Vector3>
    <Vector3>
      <x>8.158216</x>
      <y>37.1918259</y>
      <z>341.1575</z>
    </Vector3>
    <Vector3>
      <x>7.761343</x>
      <y>38.6056175</y>
      <z>341.361938</z>
    </Vector3>
    <Vector3>
      <x>7.460527</x>
      <y>40.0343361</y>
      <z>341.559174</z>
    </Vector3>
    <Vector3>
      <x>7.361998</x>
      <y>41.48754</y>
      <z>341.753021</z>
    </Vector3>
    <Vector3>
      <x>7.31081438</x>
      <y>42.94744</y>
      <z>341.945374</z>
    </Vector3>
    <Vector3>
      <x>7.290528</x>
      <y>44.41172</y>
      <z>342.1371</z>
    </Vector3>
    <Vector3>
      <x>7.27878332</x>
      <y>45.8784676</y>
      <z>342.328552</z>
    </Vector3>
    <Vector3>
      <x>7.28060341</x>
      <y>47.3478622</y>
      <z>342.520081</z>
    </Vector3>
    <Vector3>
      <x>7.29964</x>
      <y>48.82134</y>
      <z>342.712158</z>
    </Vector3>
    <Vector3>
      <x>7.31839132</x>
      <y>50.2934952</y>
      <z>342.904541</z>
    </Vector3>
    <Vector3>
      <x>7.33338451</x>
      <y>51.769577</y>
      <z>343.097839</z>
    </Vector3>
    <Vector3>
      <x>7.34748459</x>
      <y>53.24451</y>
      <z>343.2913</z>
    </Vector3>
    <Vector3>
      <x>7.35664129</x>
      <y>54.7195358</y>
      <z>343.485077</z>
    </Vector3>
    <Vector3>
      <x>7.360848</x>
      <y>56.19459</y>
      <z>343.679047</z>
    </Vector3>
    <Vector3>
      <x>7.36010027</x>
      <y>57.66967</y>
      <z>343.873047</z>
    </Vector3>
    <Vector3>
      <x>7.35535145</x>
      <y>59.14808</y>
      <z>344.0674</z>
    </Vector3>
    <Vector3>
      <x>7.34563</x>
      <y>60.62644</y>
      <z>344.2616</z>
    </Vector3>
    <Vector3>
      <x>7.33501863</x>
      <y>62.1035767</y>
      <z>344.4553</z>
    </Vector3>
    <Vector3>
      <x>7.31373835</x>
      <y>63.5822029</y>
      <z>344.648865</z>
    </Vector3>
    <Vector3>
      <x>7.207991</x>
      <y>65.04877</y>
      <z>344.840057</z>
    </Vector3>
    <Vector3>
      <x>7.07007074</x>
      <y>66.50968</y>
      <z>345.027679</z>
    </Vector3>
    <Vector3>
      <x>6.88132572</x>
      <y>67.96084</y>
      <z>345.210419</z>
    </Vector3>
    <Vector3>
      <x>6.625438</x>
      <y>69.39987</y>
      <z>345.386658</z>
    </Vector3>
    <Vector3>
      <x>6.346491</x>
      <y>70.83703</y>
      <z>345.5562</z>
    </Vector3>
    <Vector3>
      <x>6.04666328</x>
      <y>72.2700348</y>
      <z>345.718231</z>
    </Vector3>
    <Vector3>
      <x>5.74126768</x>
      <y>73.69487</y>
      <z>345.871857</z>
    </Vector3>
  </_framePos>
  <_frameRot>
    <Vector3>
      <x>0</x>
      <y>0</y>
      <z>0</z>
    </Vector3>
    <Vector3>
      <x>315.769135</x>
      <y>89.6548538</y>
      <z>90.24076</z>
    </Vector3>
    <Vector3>
      <x>338.725342</x>
      <y>89.47203</y>
      <z>90.19157</z>
    </Vector3>
    <Vector3>
      <x>349.3783</x>
      <y>89.7708</y>
      <z>90.04225</z>
    </Vector3>
    <Vector3>
      <x>355.222931</x>
      <y>89.80115</y>
      <z>90.01656</z>
    </Vector3>
    <Vector3>
      <x>358.380127</x>
      <y>89.73228</y>
      <z>90.00758</z>
    </Vector3>
    <Vector3>
      <x>0.2136676</x>
      <y>89.3891449</y>
      <z>89.99772</z>
    </Vector3>
    <Vector3>
      <x>1.24416041</x>
      <y>89.49332</y>
      <z>89.98899</z>
    </Vector3>
    <Vector3>
      <x>1.09037745</x>
      <y>89.21583</y>
      <z>89.98507</z>
    </Vector3>
    <Vector3>
      <x>0.96683526</x>
      <y>89.32668</y>
      <z>89.98864</z>
    </Vector3>
    <Vector3>
      <x>1.37739933</x>
      <y>89.1475</y>
      <z>89.9795151</z>
    </Vector3>
    <Vector3>
      <x>1.08551681</x>
      <y>89.16595</y>
      <z>89.9842</z>
    </Vector3>
    <Vector3>
      <x>0.0730266944</x>
      <y>88.98163</y>
      <z>89.99871</z>
    </Vector3>
    <Vector3>
      <x>357.9474</x>
      <y>88.8056259</y>
      <z>90.0427856</z>
    </Vector3>
    <Vector3>
      <x>351.776947</x>
      <y>88.77399</y>
      <z>90.1753845</z>
    </Vector3>
    <Vector3>
      <x>347.418549</x>
      <y>88.912</y>
      <z>90.23702</z>
    </Vector3>
    <Vector3>
      <x>342.425049</x>
      <y>88.91222</y>
      <z>90.3285</z>
    </Vector3>
    <Vector3>
      <x>336.939484</x>
      <y>88.81314</y>
      <z>90.46495</z>
    </Vector3>
    <Vector3>
      <x>330.8276</x>
      <y>88.7989655</y>
      <z>90.585495</z>
    </Vector3>
    <Vector3>
      <x>318.0043</x>
      <y>88.00924</y>
      <z>91.33226</z>
    </Vector3>
    <Vector3>
      <x>303.8887</x>
      <y>86.9800949</y>
      <z>92.50762</z>
    </Vector3>
    <Vector3>
      <x>294.143433</x>
      <y>86.08519</y>
      <z>93.5732956</z>
    </Vector3>
    <Vector3>
      <x>283.985321</x>
      <y>83.7562561</y>
      <z>96.06007</z>
    </Vector3>
    <Vector3>
      <x>277.593781</x>
      <y>79.80925</y>
      <z>100.103218</z>
    </Vector3>
    <Vector3>
      <x>273.820129</x>
      <y>71.51765</y>
      <z>108.444061</z>
    </Vector3>
    <Vector3>
      <x>272.038177</x>
      <y>56.44462</y>
      <z>123.538712</z>
    </Vector3>
    <Vector3>
      <x>271.307</x>
      <y>34.2972946</y>
      <z>145.69577</z>
    </Vector3>
    <Vector3>
      <x>271.084961</x>
      <y>13.6199274</y>
      <z>166.377731</z>
    </Vector3>
    <Vector3>
      <x>271.616272</x>
      <y>310.4345</y>
      <z>229.576767</z>
    </Vector3>
    <Vector3>
      <x>273.855957</x>
      <y>285.9375</y>
      <z>254.096741</z>
    </Vector3>
    <Vector3>
      <x>277.08493</x>
      <y>278.798828</y>
      <z>261.267334</z>
    </Vector3>
    <Vector3>
      <x>280.482147</x>
      <y>276.0354</y>
      <z>264.0646</z>
    </Vector3>
    <Vector3>
      <x>283.347</x>
      <y>274.767151</y>
      <z>265.361023</z>
    </Vector3>
    <Vector3>
      <x>286.80957</x>
      <y>273.848175</y>
      <z>266.3158</z>
    </Vector3>
    <Vector3>
      <x>289.647858</x>
      <y>273.3008</y>
      <z>266.891</z>
    </Vector3>
    <Vector3>
      <x>292.3831</x>
      <y>272.908051</y>
      <z>267.31073</z>
    </Vector3>
    <Vector3>
      <x>294.0533</x>
      <y>272.694672</y>
      <z>267.539</z>
    </Vector3>
    <Vector3>
      <x>295.131653</x>
      <y>272.566437</y>
      <z>267.676239</z>
    </Vector3>
    <Vector3>
      <x>295.670563</x>
      <y>272.5009</y>
      <z>267.745667</z>
    </Vector3>
    <Vector3>
      <x>296.122955</x>
      <y>272.445</y>
      <z>267.8045</z>
    </Vector3>
    <Vector3>
      <x>296.494751</x>
      <y>272.402222</y>
      <z>267.849823</z>
    </Vector3>
    <Vector3>
      <x>296.680664</x>
      <y>272.38</y>
      <z>267.873169</z>
    </Vector3>
    <Vector3>
      <x>296.773468</x>
      <y>272.368622</y>
      <z>267.885071</z>
    </Vector3>
    <Vector3>
      <x>296.819946</x>
      <y>272.3626</y>
      <z>267.8913</z>
    </Vector3>
    <Vector3>
      <x>296.589264</x>
      <y>272.37</y>
      <z>267.880432</z>
    </Vector3>
    <Vector3>
      <x>294.608337</x>
      <y>272.524078</y>
      <z>267.704926</z>
    </Vector3>
    <Vector3>
      <x>283.881439</x>
      <y>276.508575</y>
      <z>263.679932</z>
    </Vector3>
    <Vector3>
      <x>278.19986</x>
      <y>280.089325</y>
      <z>260.011749</z>
    </Vector3>
    <Vector3>
      <x>274.344421</x>
      <y>287.39856</y>
      <z>252.6484</z>
    </Vector3>
    <Vector3>
      <x>272.4812</x>
      <y>298.3028</y>
      <z>241.71962</z>
    </Vector3>
    <Vector3>
      <x>274.418823</x>
      <y>71.3897552</y>
      <z>108.558708</z>
    </Vector3>
    <Vector3>
      <x>280.107056</x>
      <y>81.4078751</y>
      <z>98.46074</z>
    </Vector3>
    <Vector3>
      <x>283.949829</x>
      <y>84.16507</y>
      <z>95.66398</z>
    </Vector3>
    <Vector3>
      <x>288.000641</x>
      <y>85.53645</y>
      <z>94.24589</z>
    </Vector3>
    <Vector3>
      <x>291.056824</x>
      <y>86.37292</y>
      <z>93.38547</z>
    </Vector3>
    <Vector3>
      <x>296.621063</x>
      <y>86.58662</y>
      <z>93.05226</z>
    </Vector3>
    <Vector3>
      <x>300.358948</x>
      <y>87.10213</y>
      <z>92.50105</z>
    </Vector3>
    <Vector3>
      <x>302.8641</x>
      <y>87.5111</y>
      <z>92.0909653</z>
    </Vector3>
    <Vector3>
      <x>304.532837</x>
      <y>87.7844849</y>
      <z>91.82544</z>
    </Vector3>
    <Vector3>
      <x>305.624817</x>
      <y>87.9553146</y>
      <z>91.66226</z>
    </Vector3>
    <Vector3>
      <x>305.9581</x>
      <y>88.07041</y>
      <z>91.56211</z>
    </Vector3>
    <Vector3>
      <x>305.3037</x>
      <y>88.10681</y>
      <z>91.54522</z>
    </Vector3>
    <Vector3>
      <x>303.0779</x>
      <y>87.9443359</y>
      <z>91.7227249</z>
    </Vector3>
    <Vector3>
      <x>298.3115</x>
      <y>86.9753647</y>
      <z>92.66339</z>
    </Vector3>
    <Vector3>
      <x>293.924835</x>
      <y>85.97231</y>
      <z>93.6826248</z>
    </Vector3>
    <Vector3>
      <x>282.3549</x>
      <y>71.8825</y>
      <z>107.724464</z>
    </Vector3>
    <Vector3>
      <x>276.396881</x>
      <y>61.2013969</y>
      <z>118.647804</z>
    </Vector3>
    <Vector3>
      <x>273.4488</x>
      <y>49.6019974</y>
      <z>130.346741</z>
    </Vector3>
    <Vector3>
      <x>272.057556</x>
      <y>34.87423</y>
      <z>145.108444</z>
    </Vector3>
    <Vector3>
      <x>271.455078</x>
      <y>18.6681252</y>
      <z>161.326263</z>
    </Vector3>
    <Vector3>
      <x>271.2174</x>
      <y>5.460148</y>
      <z>174.538635</z>
    </Vector3>
    <Vector3>
      <x>271.125</x>
      <y>357.100677</y>
      <z>182.899872</z>
    </Vector3>
    <Vector3>
      <x>272.106171</x>
      <y>302.8219</y>
      <z>237.195724</z>
    </Vector3>
    <Vector3>
      <x>274.828644</x>
      <y>284.6038</y>
      <z>255.445831</z>
    </Vector3>
    <Vector3>
      <x>278.663025</x>
      <y>278.46936</y>
      <z>261.625916</z>
    </Vector3>
    <Vector3>
      <x>286.11853</x>
      <y>275.262177</y>
      <z>264.943573</z>
    </Vector3>
    <Vector3>
      <x>292.9927</x>
      <y>273.709564</y>
      <z>266.5844</z>
    </Vector3>
    <Vector3>
      <x>299.4658</x>
      <y>272.781036</y>
      <z>267.578247</z>
    </Vector3>
    <Vector3>
      <x>305.8385</x>
      <y>272.1806</y>
      <z>268.231964</z>
    </Vector3>
    <Vector3>
      <x>314.699219</x>
      <y>271.766327</y>
      <z>268.744263</z>
    </Vector3>
    <Vector3>
      <x>321.6606</x>
      <y>271.4987</y>
      <z>269.070221</z>
    </Vector3>
    <Vector3>
      <x>327.555267</x>
      <y>271.323059</y>
      <z>269.2901</z>
    </Vector3>
    <Vector3>
      <x>332.785583</x>
      <y>271.206573</y>
      <z>269.448151</z>
    </Vector3>
    <Vector3>
      <x>337.8584</x>
      <y>271.121643</y>
      <z>269.5772</z>
    </Vector3>
    <Vector3>
      <x>344.5011</x>
      <y>271.059143</y>
      <z>269.716949</z>
    </Vector3>
    <Vector3>
      <x>349.447937</x>
      <y>271.0275</y>
      <z>269.811829</z>
    </Vector3>
    <Vector3>
      <x>353.074615</x>
      <y>271.0158</y>
      <z>269.8775</z>
    </Vector3>
    <Vector3>
      <x>355.914856</x>
      <y>271.02594</y>
      <z>269.9269</z>
    </Vector3>
    <Vector3>
      <x>357.72522</x>
      <y>271.03476</y>
      <z>269.958923</z>
    </Vector3>
    <Vector3>
      <x>359.0275</x>
      <y>271.0406</y>
      <z>269.98233</z>
    </Vector3>
    <Vector3>
      <x>359.678925</x>
      <y>271.045074</y>
      <z>269.994141</z>
    </Vector3>
    <Vector3>
      <x>358.5432</x>
      <y>271.0364</y>
      <z>269.973663</z>
    </Vector3>
    <Vector3>
      <x>348.670868</x>
      <y>271.071228</y>
      <z>269.789551</z>
    </Vector3>
    <Vector3>
      <x>327.8647</x>
      <y>271.2625</y>
      <z>269.328369</z>
    </Vector3>
    <Vector3>
      <x>304.227142</x>
      <y>272.773132</y>
      <z>267.706573</z>
    </Vector3>
    <Vector3>
      <x>287.2803</x>
      <y>275.541077</y>
      <z>264.707581</z>
    </Vector3>
    <Vector3>
      <x>277.154266</x>
      <y>280.949829</y>
      <z>259.1334</z>
    </Vector3>
    <Vector3>
      <x>271.2124</x>
      <y>335.387756</y>
      <z>204.617081</z>
    </Vector3>
    <Vector3>
      <x>274.755127</x>
      <y>78.86028</y>
      <z>101.102325</z>
    </Vector3>
    <Vector3>
      <x>282.685059</x>
      <y>110.440636</y>
      <z>70.01836</z>
    </Vector3>
    <Vector3>
      <x>288.976379</x>
      <y>102.225128</y>
      <z>78.42084</z>
    </Vector3>
    <Vector3>
      <x>293.5481</x>
      <y>95.9218445</y>
      <z>84.56822</z>
    </Vector3>
    <Vector3>
      <x>295.980255</x>
      <y>91.96295</y>
      <z>88.23528</z>
    </Vector3>
    <Vector3>
      <x>297.850159</x>
      <y>89.92661</y>
      <z>90.06489</z>
    </Vector3>
    <Vector3>
      <x>299.7098</x>
      <y>88.94379</y>
      <z>90.9174</z>
    </Vector3>
    <Vector3>
      <x>300.8193</x>
      <y>88.44319</y>
      <z>91.33706</z>
    </Vector3>
    <Vector3>
      <x>301.458618</x>
      <y>88.203476</y>
      <z>91.5326</z>
    </Vector3>
    <Vector3>
      <x>301.818939</x>
      <y>88.10099</y>
      <z>91.6137848</z>
    </Vector3>
    <Vector3>
      <x>301.6787</x>
      <y>88.07013</y>
      <z>91.6425</z>
    </Vector3>
    <Vector3>
      <x>291.5469</x>
      <y>96.0777359</y>
      <z>84.34414</z>
    </Vector3>
    <Vector3>
      <x>280.735382</x>
      <y>108.843346</y>
      <z>71.4637451</z>
    </Vector3>
    <Vector3>
      <x>274.1763</x>
      <y>119.089638</y>
      <z>60.9750443</z>
    </Vector3>
    <Vector3>
      <x>279.315277</x>
      <y>256.85257</y>
      <z>282.97998</z>
    </Vector3>
    <Vector3>
      <x>289.589844</x>
      <y>266.12085</y>
      <z>273.655243</z>
    </Vector3>
    <Vector3>
      <x>297.399384</x>
      <y>269.0431</y>
      <z>270.849548</z>
    </Vector3>
    <Vector3>
      <x>304.381775</x>
      <y>270.223541</y>
      <z>269.815521</z>
    </Vector3>
    <Vector3>
      <x>310.952545</x>
      <y>270.7159</y>
      <z>269.4593</z>
    </Vector3>
    <Vector3>
      <x>317.047241</x>
      <y>270.9292</y>
      <z>269.366821</z>
    </Vector3>
    <Vector3>
      <x>324.641357</x>
      <y>270.979462</y>
      <z>269.433167</z>
    </Vector3>
    <Vector3>
      <x>330.194183</x>
      <y>271.0223</y>
      <z>269.491821</z>
    </Vector3>
    <Vector3>
      <x>335.48056</x>
      <y>271.0347</y>
      <z>269.570557</z>
    </Vector3>
    <Vector3>
      <x>338.875519</x>
      <y>271.042175</y>
      <z>269.624359</z>
    </Vector3>
    <Vector3>
      <x>342.21048</x>
      <y>271.038666</y>
      <z>269.682617</z>
    </Vector3>
    <Vector3>
      <x>346.148529</x>
      <y>271.035278</y>
      <z>269.752136</z>
    </Vector3>
    <Vector3>
      <x>348.708221</x>
      <y>271.0296</y>
      <z>269.79837</z>
    </Vector3>
    <Vector3>
      <x>350.376953</x>
      <y>271.027924</y>
      <z>269.828156</z>
    </Vector3>
    <Vector3>
      <x>351.4742</x>
      <y>271.028625</y>
      <z>269.847473</z>
    </Vector3>
    <Vector3>
      <x>352.156342</x>
      <y>271.023834</y>
      <z>269.86026</z>
    </Vector3>
    <Vector3>
      <x>350.7516</x>
      <y>271.0028</y>
      <z>269.8388</z>
    </Vector3>
    <Vector3>
      <x>347.2749</x>
      <y>270.982452</y>
      <z>269.7836</z>
    </Vector3>
    <Vector3>
      <x>342.3379</x>
      <y>270.9663</y>
      <z>269.7068</z>
    </Vector3>
    <Vector3>
      <x>336.430969</x>
      <y>270.961823</y>
      <z>269.6154</z>
    </Vector3>
    <Vector3>
      <x>324.9086</x>
      <y>271.1062</y>
      <z>269.364</z>
    </Vector3>
    <Vector3>
      <x>308.011963</x>
      <y>270.673828</y>
      <z>269.4691</z>
    </Vector3>
    <Vector3>
      <x>297.839478</x>
      <y>270.8696</y>
      <z>269.231049</z>
    </Vector3>
    <Vector3>
      <x>289.3817</x>
      <y>271.486755</y>
      <z>268.597443</z>
    </Vector3>
    <Vector3>
      <x>279.789978</x>
      <y>271.597931</y>
      <z>268.425323</z>
    </Vector3>
    <Vector3>
      <x>275.019653</x>
      <y>275.737549</y>
      <z>264.284332</z>
    </Vector3>
    <Vector3>
      <x>271.417328</x>
      <y>297.284454</y>
      <z>242.722748</z>
    </Vector3>
    <Vector3>
      <x>272.3052</x>
      <y>71.61595</y>
      <z>108.370148</z>
    </Vector3>
    <Vector3>
      <x>275.3426</x>
      <y>81.57471</y>
      <z>98.38922</z>
    </Vector3>
    <Vector3>
      <x>278.200531</x>
      <y>84.21421</y>
      <z>95.7270355</z>
    </Vector3>
    <Vector3>
      <x>281.334137</x>
      <y>85.82811</y>
      <z>94.0908051</z>
    </Vector3>
    <Vector3>
      <x>286.154236</x>
      <y>87.63299</y>
      <z>92.27365</z>
    </Vector3>
    <Vector3>
      <x>291.1067</x>
      <y>88.46133</y>
      <z>91.43549</z>
    </Vector3>
    <Vector3>
      <x>295.080078</x>
      <y>88.55457</y>
      <z>91.3092041</z>
    </Vector3>
    <Vector3>
      <x>297.757568</x>
      <y>88.38585</y>
      <z>91.42849</z>
    </Vector3>
    <Vector3>
      <x>300.2494</x>
      <y>88.32746</y>
      <z>91.4449158</z>
    </Vector3>
    <Vector3>
      <x>302.903168</x>
      <y>88.35918</y>
      <z>91.37773</z>
    </Vector3>
    <Vector3>
      <x>304.5697</x>
      <y>88.2994156</y>
      <z>91.40046</z>
    </Vector3>
    <Vector3>
      <x>305.701019</x>
      <y>88.24991</y>
      <z>91.42136</z>
    </Vector3>
    <Vector3>
      <x>306.4049</x>
      <y>88.2184143</y>
      <z>91.43407</z>
    </Vector3>
    <Vector3>
      <x>306.1568</x>
      <y>88.1863251</y>
      <z>91.46454</z>
    </Vector3>
    <Vector3>
      <x>301.977356</x>
      <y>88.26581</y>
      <z>91.4711761</z>
    </Vector3>
    <Vector3>
      <x>289.062</x>
      <y>90.5102</y>
      <z>89.51778</z>
    </Vector3>
    <Vector3>
      <x>279.383728</x>
      <y>90.8647156</y>
      <z>89.14686</z>
    </Vector3>
    <Vector3>
      <x>274.573</x>
      <y>86.10833</y>
      <z>93.87931</z>
    </Vector3>
    <Vector3>
      <x>273.866882</x>
      <y>275.594421</y>
      <z>264.418274</z>
    </Vector3>
    <Vector3>
      <x>280.254578</x>
      <y>273.165466</y>
      <z>266.885</z>
    </Vector3>
    <Vector3>
      <x>292.618164</x>
      <y>271.441162</y>
      <z>268.669617</z>
    </Vector3>
    <Vector3>
      <x>298.80368</x>
      <y>271.6787</y>
      <z>268.52887</z>
    </Vector3>
    <Vector3>
      <x>306.9768</x>
      <y>271.453369</y>
      <z>268.838837</z>
    </Vector3>
    <Vector3>
      <x>317.0047</x>
      <y>271.2808</y>
      <z>269.1265</z>
    </Vector3>
    <Vector3>
      <x>323.4002</x>
      <y>271.2205</y>
      <z>269.272247</z>
    </Vector3>
    <Vector3>
      <x>329.248657</x>
      <y>271.181824</y>
      <z>269.39566</z>
    </Vector3>
    <Vector3>
      <x>334.5734</x>
      <y>271.154327</y>
      <z>269.504333</z>
    </Vector3>
    <Vector3>
      <x>339.652649</x>
      <y>271.137756</y>
      <z>269.60434</z>
    </Vector3>
    <Vector3>
      <x>346.455353</x>
      <y>271.227783</y>
      <z>269.7124</z>
    </Vector3>
    <Vector3>
      <x>350.853455</x>
      <y>271.196838</y>
      <z>269.809723</z>
    </Vector3>
    <Vector3>
      <x>353.738617</x>
      <y>271.15033</y>
      <z>269.8745</z>
    </Vector3>
    <Vector3>
      <x>355.6083</x>
      <y>271.112732</y>
      <z>269.9148</z>
    </Vector3>
    <Vector3>
      <x>356.6964</x>
      <y>271.0875</y>
      <z>269.937317</z>
    </Vector3>
    <Vector3>
      <x>356.101959</x>
      <y>271.0362</y>
      <z>269.929565</z>
    </Vector3>
    <Vector3>
      <x>345.7989</x>
      <y>271.595856</y>
      <z>269.6084</z>
    </Vector3>
    <Vector3>
      <x>338.498962</x>
      <y>271.619873</y>
      <z>269.406158</z>
    </Vector3>
    <Vector3>
      <x>320.324768</x>
      <y>272.603546</y>
      <z>268.337128</z>
    </Vector3>
    <Vector3>
      <x>301.616516</x>
      <y>273.582825</y>
      <z>266.947845</z>
    </Vector3>
    <Vector3>
      <x>284.470428</x>
      <y>275.552582</y>
      <z>264.622528</z>
    </Vector3>
    <Vector3>
      <x>274.100647</x>
      <y>286.01825</y>
      <z>254.020691</z>
    </Vector3>
    <Vector3>
      <x>274.3429</x>
      <y>77.30231</y>
      <z>102.662422</z>
    </Vector3>
    <Vector3>
      <x>286.91925</x>
      <y>88.06969</y>
      <z>91.8468246</z>
    </Vector3>
    <Vector3>
      <x>295.564148</x>
      <y>88.69404</y>
      <z>91.178154</z>
    </Vector3>
    <Vector3>
      <x>301.905457</x>
      <y>88.78426</y>
      <z>91.03211</z>
    </Vector3>
    <Vector3>
      <x>306.1544</x>
      <y>88.71375</y>
      <z>91.03861</z>
    </Vector3>
    <Vector3>
      <x>309.035278</x>
      <y>88.64367</y>
      <z>91.05361</z>
    </Vector3>
    <Vector3>
      <x>310.752747</x>
      <y>88.58043</y>
      <z>91.07548</z>
    </Vector3>
    <Vector3>
      <x>312.200378</x>
      <y>88.569</y>
      <z>91.0601959</z>
    </Vector3>
    <Vector3>
      <x>312.6453</x>
      <y>88.532486</y>
      <z>91.07955</z>
    </Vector3>
    <Vector3>
      <x>304.011627</x>
      <y>88.81019</y>
      <z>90.98632</z>
    </Vector3>
    <Vector3>
      <x>286.886536</x>
      <y>89.0630341</y>
      <z>90.89657</z>
    </Vector3>
    <Vector3>
      <x>278.3391</x>
      <y>86.47558</y>
      <z>93.48727</z>
    </Vector3>
    <Vector3>
      <x>275.541534</x>
      <y>277.503967</y>
      <z>262.5307</z>
    </Vector3>
    <Vector3>
      <x>286.4442</x>
      <y>273.272583</y>
      <z>266.861023</z>
    </Vector3>
    <Vector3>
      <x>293.473633</x>
      <y>272.56073</y>
      <z>267.65094</z>
    </Vector3>
    <Vector3>
      <x>300.328918</x>
      <y>272.1496</y>
      <z>268.1444</z>
    </Vector3>
    <Vector3>
      <x>307.092468</x>
      <y>271.887726</y>
      <z>268.494019</z>
    </Vector3>
    <Vector3>
      <x>316.086853</x>
      <y>271.856659</y>
      <z>268.712036</z>
    </Vector3>
    <Vector3>
      <x>322.793762</x>
      <y>271.683441</y>
      <z>268.981873</z>
    </Vector3>
    <Vector3>
      <x>328.1464</x>
      <y>271.526428</y>
      <z>269.194275</z>
    </Vector3>
    <Vector3>
      <x>332.575317</x>
      <y>271.405518</y>
      <z>269.352539</z>
    </Vector3>
    <Vector3>
      <x>336.4577</x>
      <y>271.321716</y>
      <z>269.472</z>
    </Vector3>
    <Vector3>
      <x>340.8072</x>
      <y>271.309723</y>
      <z>269.569366</z>
    </Vector3>
    <Vector3>
      <x>343.754669</x>
      <y>271.235474</y>
      <z>269.654327</z>
    </Vector3>
    <Vector3>
      <x>345.7323</x>
      <y>271.1664</y>
      <z>269.7125</z>
    </Vector3>
    <Vector3>
      <x>347.043549</x>
      <y>271.1172</y>
      <z>269.749481</z>
    </Vector3>
    <Vector3>
      <x>347.909149</x>
      <y>271.083618</y>
      <z>269.77298</z>
    </Vector3>
    <Vector3>
      <x>348.5076</x>
      <y>271.062927</y>
      <z>269.7882</z>
    </Vector3>
    <Vector3>
      <x>346.917664</x>
      <y>271.052765</y>
      <z>269.7617</z>
    </Vector3>
    <Vector3>
      <x>336.016235</x>
      <y>272.447449</y>
      <z>269.004639</z>
    </Vector3>
    <Vector3>
      <x>330.5196</x>
      <y>272.277649</y>
      <z>268.878662</z>
    </Vector3>
    <Vector3>
      <x>316.983521</x>
      <y>273.638977</y>
      <z>267.5157</z>
    </Vector3>
    <Vector3>
      <x>293.795837</x>
      <y>279.6288</y>
      <z>261.17627</z>
    </Vector3>
    <Vector3>
      <x>276.6573</x>
      <y>299.3793</y>
      <z>240.786133</z>
    </Vector3>
    <Vector3>
      <x>275.455139</x>
      <y>63.9925537</y>
      <z>115.90509</z>
    </Vector3>
    <Vector3>
      <x>282.2054</x>
      <y>81.49076</y>
      <z>98.31962</z>
    </Vector3>
    <Vector3>
      <x>287.602325</x>
      <y>85.22105</y>
      <z>94.55617</z>
    </Vector3>
    <Vector3>
      <x>293.439026</x>
      <y>86.87791</y>
      <z>92.86493</z>
    </Vector3>
    <Vector3>
      <x>297.617371</x>
      <y>87.5369949</y>
      <z>92.18268</z>
    </Vector3>
    <Vector3>
      <x>299.9706</x>
      <y>87.79735</y>
      <z>91.9083557</z>
    </Vector3>
    <Vector3>
      <x>301.532349</x>
      <y>87.92657</y>
      <z>91.7674942</z>
    </Vector3>
    <Vector3>
      <x>302.680939</x>
      <y>88.0023346</y>
      <z>91.68163</z>
    </Vector3>
    <Vector3>
      <x>303.200226</x>
      <y>88.0334244</y>
      <z>91.64575</z>
    </Vector3>
    <Vector3>
      <x>303.086426</x>
      <y>88.04119</y>
      <z>91.6413651</z>
    </Vector3>
    <Vector3>
      <x>301.421</x>
      <y>87.9613</y>
      <z>91.7399445</z>
    </Vector3>
    <Vector3>
      <x>290.574</x>
      <y>86.90156</y>
      <z>92.90118</z>
    </Vector3>
    <Vector3>
      <x>278.751</x>
      <y>82.19082</y>
      <z>97.71939</z>
    </Vector3>
    <Vector3>
      <x>271.3535</x>
      <y>29.2852325</y>
      <z>150.707932</z>
    </Vector3>
    <Vector3>
      <x>281.965027</x>
      <y>277.709625</y>
      <z>262.455933</z>
    </Vector3>
    <Vector3>
      <x>291.638</x>
      <y>274.5592</y>
      <z>265.760864</z>
    </Vector3>
    <Vector3>
      <x>299.4886</x>
      <y>273.351318</y>
      <z>267.082</z>
    </Vector3>
    <Vector3>
      <x>309.879242</x>
      <y>273.394043</y>
      <z>267.394165</z>
    </Vector3>
    <Vector3>
      <x>317.834076</x>
      <y>272.958374</y>
      <z>268.013153</z>
    </Vector3>
    <Vector3>
      <x>324.1457</x>
      <y>272.538849</y>
      <z>268.5123</z>
    </Vector3>
    <Vector3>
      <x>330.1625</x>
      <y>272.3512</y>
      <z>268.829681</z>
    </Vector3>
    <Vector3>
      <x>333.917755</x>
      <y>271.938629</y>
      <z>269.1474</z>
    </Vector3>
    <Vector3>
      <x>338.351746</x>
      <y>271.849182</y>
      <z>269.317627</z>
    </Vector3>
    <Vector3>
      <x>341.265747</x>
      <y>271.6181</y>
      <z>269.480164</z>
    </Vector3>
    <Vector3>
      <x>343.153259</x>
      <y>271.4166</y>
      <z>269.5894</z>
    </Vector3>
    <Vector3>
      <x>344.404663</x>
      <y>271.281</y>
      <z>269.655579</z>
    </Vector3>
    <Vector3>
      <x>345.247253</x>
      <y>271.196533</y>
      <z>269.695251</z>
    </Vector3>
    <Vector3>
      <x>345.6909</x>
      <y>271.1285</y>
      <z>269.721069</z>
    </Vector3>
    <Vector3>
      <x>344.2321</x>
      <y>271.078857</y>
      <z>269.7068</z>
    </Vector3>
    <Vector3>
      <x>342.028961</x>
      <y>271.105042</y>
      <z>269.659</z>
    </Vector3>
    <Vector3>
      <x>332.221527</x>
      <y>274.5972</y>
      <z>267.853851</z>
    </Vector3>
    <Vector3>
      <x>306.661926</x>
      <y>288.6629</y>
      <z>254.840149</z>
    </Vector3>
    <Vector3>
      <x>285.4228</x>
      <y>309.355255</y>
      <z>231.671158</z>
    </Vector3>
    <Vector3>
      <x>276.315918</x>
      <y>0.154106066</y>
      <z>179.844955</z>
    </Vector3>
    <Vector3>
      <x>278.198059</x>
      <y>60.8468361</y>
      <z>118.903473</z>
    </Vector3>
    <Vector3>
      <x>282.414825</x>
      <y>77.6228561</y>
      <z>102.096344</z>
    </Vector3>
    <Vector3>
      <x>285.915771</x>
      <y>83.02215</y>
      <z>96.71286</z>
    </Vector3>
    <Vector3>
      <x>290.445068</x>
      <y>85.63012</y>
      <z>94.09559</z>
    </Vector3>
    <Vector3>
      <x>294.2515</x>
      <y>86.80037</y>
      <z>92.91779</z>
    </Vector3>
    <Vector3>
      <x>297.301117</x>
      <y>87.38193</y>
      <z>92.32678</z>
    </Vector3>
    <Vector3>
      <x>299.635345</x>
      <y>87.68957</y>
      <z>92.00848</z>
    </Vector3>
    <Vector3>
      <x>301.364838</x>
      <y>87.85944</y>
      <z>91.8279953</z>
    </Vector3>
    <Vector3>
      <x>302.849</x>
      <y>87.9665451</y>
      <z>91.70853</z>
    </Vector3>
    <Vector3>
      <x>303.403</x>
      <y>88.0136261</y>
      <z>91.65848</z>
    </Vector3>
    <Vector3>
      <x>293.634064</x>
      <y>87.2400055</y>
      <z>92.52882</z>
    </Vector3>
    <Vector3>
      <x>281.743317</x>
      <y>84.565</y>
      <z>95.32191</z>
    </Vector3>
    <Vector3>
      <x>274.6176</x>
      <y>76.71768</y>
      <z>103.240723</z>
    </Vector3>
    <Vector3>
      <x>271.9889</x>
      <y>301.496277</y>
      <z>238.5191</z>
    </Vector3>
    <Vector3>
      <x>283.421478</x>
      <y>275.136078</y>
      <z>265.003479</z>
    </Vector3>
    <Vector3>
      <x>290.664856</x>
      <y>273.240631</y>
      <z>266.967468</z>
    </Vector3>
    <Vector3>
      <x>296.273529</x>
      <y>272.460266</y>
      <z>267.79364</z>
    </Vector3>
    <Vector3>
      <x>303.055725</x>
      <y>271.8756</y>
      <z>268.427826</z>
    </Vector3>
    <Vector3>
      <x>308.868683</x>
      <y>271.477753</y>
      <z>268.849365</z>
    </Vector3>
    <Vector3>
      <x>312.559326</x>
      <y>271.259033</y>
      <z>269.072571</z>
    </Vector3>
    <Vector3>
      <x>316.005524</x>
      <y>271.029</y>
      <z>269.285248</z>
    </Vector3>
    <Vector3>
      <x>318.370239</x>
      <y>270.938873</y>
      <z>269.376251</z>
    </Vector3>
    <Vector3>
      <x>320.223145</x>
      <y>270.89447</y>
      <z>269.4277</z>
    </Vector3>
    <Vector3>
      <x>321.278961</x>
      <y>270.9792</y>
      <z>269.387451</z>
    </Vector3>
    <Vector3>
      <x>321.945923</x>
      <y>271.0628</y>
      <z>269.344849</z>
    </Vector3>
    <Vector3>
      <x>322.1943</x>
      <y>271.1451</y>
      <z>269.298</z>
    </Vector3>
    <Vector3>
      <x>322.035828</x>
      <y>271.199982</y>
      <z>269.261749</z>
    </Vector3>
    <Vector3>
      <x>321.358551</x>
      <y>271.213165</y>
      <z>269.242371</z>
    </Vector3>
    <Vector3>
      <x>320.797424</x>
      <y>271.210541</y>
      <z>269.2348</z>
    </Vector3>
    <Vector3>
      <x>320.263031</x>
      <y>271.1996</y>
      <z>269.2331</z>
    </Vector3>
    <Vector3>
      <x>319.066162</x>
      <y>271.1996</y>
      <z>269.214</z>
    </Vector3>
    <Vector3>
      <x>317.289581</x>
      <y>271.197632</y>
      <z>269.187561</z>
    </Vector3>
    <Vector3>
      <x>313.6139</x>
      <y>271.0922</y>
      <z>269.2092</z>
    </Vector3>
    <Vector3>
      <x>310.46756</x>
      <y>271.165222</y>
      <z>269.1135</z>
    </Vector3>
    <Vector3>
      <x>307.677765</x>
      <y>271.300049</y>
      <z>268.971</z>
    </Vector3>
    <Vector3>
      <x>304.406616</x>
      <y>271.424652</y>
      <z>268.824524</z>
    </Vector3>
    <Vector3>
      <x>302.089783</x>
      <y>271.604218</y>
      <z>268.640778</z>
    </Vector3>
    <Vector3>
      <x>298.5607</x>
      <y>271.786682</y>
      <z>268.430634</z>
    </Vector3>
    <Vector3>
      <x>296.384918</x>
      <y>272.0203</y>
      <z>268.19</z>
    </Vector3>
    <Vector3>
      <x>295.032623</x>
      <y>272.2048</y>
      <z>268.002136</z>
    </Vector3>
    <Vector3>
      <x>294.491516</x>
      <y>272.310425</y>
      <z>267.897247</z>
    </Vector3>
    <Vector3>
      <x>294.550659</x>
      <y>272.33728</y>
      <z>267.8738</z>
    </Vector3>
    <Vector3>
      <x>296.3378</x>
      <y>272.151917</y>
      <z>268.0713</z>
    </Vector3>
    <Vector3>
      <x>298.758148</x>
      <y>271.9368</y>
      <z>268.301941</z>
    </Vector3>
    <Vector3>
      <x>300.881226</x>
      <y>271.8267</y>
      <z>268.432129</z>
    </Vector3>
    <Vector3>
      <x>302.609161</x>
      <y>271.7806</y>
      <z>268.499939</z>
    </Vector3>
    <Vector3>
      <x>303.8661</x>
      <y>271.776245</y>
      <z>268.524933</z>
    </Vector3>
    <Vector3>
      <x>305.020447</x>
      <y>271.764069</y>
      <z>268.555176</z>
    </Vector3>
    <Vector3>
      <x>305.6385</x>
      <y>271.772339</y>
      <z>268.559448</z>
    </Vector3>
    <Vector3>
      <x>306.0528</x>
      <y>271.781525</y>
      <z>268.55954</z>
    </Vector3>
    <Vector3>
      <x>306.26004</x>
      <y>271.790161</y>
      <z>268.556335</z>
    </Vector3>
    <Vector3>
      <x>306.49472</x>
      <y>271.793823</y>
      <z>268.55777</z>
    </Vector3>
    <Vector3>
      <x>307.880249</x>
      <y>271.715332</y>
      <z>268.645935</z>
    </Vector3>
    <Vector3>
      <x>309.4133</x>
      <y>271.6324</y>
      <z>268.7387</z>
    </Vector3>
    <Vector3>
      <x>310.910339</x>
      <y>271.560974</y>
      <z>268.8202</z>
    </Vector3>
    <Vector3>
      <x>312.206726</x>
      <y>271.510956</y>
      <z>268.880676</z>
    </Vector3>
    <Vector3>
      <x>313.399933</x>
      <y>271.46463</y>
      <z>268.93573</z>
    </Vector3>
    <Vector3>
      <x>314.233734</x>
      <y>271.443085</y>
      <z>268.965942</z>
    </Vector3>
    <Vector3>
      <x>314.650848</x>
      <y>271.439575</y>
      <z>268.975769</z>
    </Vector3>
    <Vector3>
      <x>314.928864</x>
      <y>271.4345</y>
      <z>268.984283</z>
    </Vector3>
    <Vector3>
      <x>314.175262</x>
      <y>271.43573</y>
      <z>268.970184</z>
    </Vector3>
    <Vector3>
      <x>310.029</x>
      <y>271.421844</y>
      <z>268.911163</z>
    </Vector3>
    <Vector3>
      <x>306.1438</x>
      <y>271.491241</y>
      <z>268.795654</z>
    </Vector3>
    <Vector3>
      <x>302.042664</x>
      <y>271.624847</y>
      <z>268.6226</z>
    </Vector3>
    <Vector3>
      <x>297.719421</x>
      <y>271.840576</y>
      <z>268.370544</z>
    </Vector3>
    <Vector3>
      <x>292.314728</x>
      <y>272.4185</y>
      <z>267.762451</z>
    </Vector3>
    <Vector3>
      <x>281.2897</x>
      <y>274.185822</y>
      <z>265.8949</z>
    </Vector3>
    <Vector3>
      <x>275.809937</x>
      <y>278.784363</y>
      <z>261.260071</z>
    </Vector3>
    <Vector3>
      <x>273.756561</x>
      <y>75.03672</y>
      <z>104.932587</z>
    </Vector3>
    <Vector3>
      <x>280.0215</x>
      <y>84.057785</y>
      <z>95.85219</z>
    </Vector3>
    <Vector3>
      <x>291.636078</x>
      <y>86.3494339</y>
      <z>93.39399</z>
    </Vector3>
    <Vector3>
      <x>300.7191</x>
      <y>87.23583</y>
      <z>92.37679</z>
    </Vector3>
    <Vector3>
      <x>308.210052</x>
      <y>87.73134</y>
      <z>91.78295</z>
    </Vector3>
    <Vector3>
      <x>314.8786</x>
      <y>88.0363541</y>
      <z>91.39173</z>
    </Vector3>
    <Vector3>
      <x>320.673767</x>
      <y>88.2476959</y>
      <z>91.1107</z>
    </Vector3>
    <Vector3>
      <x>325.621429</x>
      <y>88.40471</y>
      <z>90.9009552</z>
    </Vector3>
    <Vector3>
      <x>332.293732</x>
      <y>88.36733</y>
      <z>90.7592545</z>
    </Vector3>
    <Vector3>
      <x>336.678223</x>
      <y>88.50662</y>
      <z>90.5913239</z>
    </Vector3>
    <Vector3>
      <x>339.5818</x>
      <y>88.64043</y>
      <z>90.47439</z>
    </Vector3>
    <Vector3>
      <x>341.298218</x>
      <y>88.74077</y>
      <z>90.4038239</z>
    </Vector3>
    <Vector3>
      <x>342.521179</x>
      <y>88.79936</y>
      <z>90.3606644</z>
    </Vector3>
    <Vector3>
      <x>343.568054</x>
      <y>88.82967</y>
      <z>90.33111</z>
    </Vector3>
    <Vector3>
      <x>344.183716</x>
      <y>88.85161</y>
      <z>90.31304</z>
    </Vector3>
    <Vector3>
      <x>344.512054</x>
      <y>88.86215</y>
      <z>90.30389</z>
    </Vector3>
    <Vector3>
      <x>344.756866</x>
      <y>88.86878</y>
      <z>90.29746</z>
    </Vector3>
    <Vector3>
      <x>344.879272</x>
      <y>88.87239</y>
      <z>90.29418</z>
    </Vector3>
    <Vector3>
      <x>344.9405</x>
      <y>88.87434</y>
      <z>90.29251</z>
    </Vector3>
    <Vector3>
      <x>344.9711</x>
      <y>88.8753052</y>
      <z>90.29168</z>
    </Vector3>
    <Vector3>
      <x>345.0041</x>
      <y>88.8735657</y>
      <z>90.29151</z>
    </Vector3>
    <Vector3>
      <x>345.020569</x>
      <y>88.87269</y>
      <z>90.29142</z>
    </Vector3>
    <Vector3>
      <x>345.1095</x>
      <y>88.8735</y>
      <z>90.28951</z>
    </Vector3>
    <Vector3>
      <x>345.040833</x>
      <y>88.8719559</y>
      <z>90.29122</z>
    </Vector3>
    <Vector3>
      <x>343.427368</x>
      <y>88.81756</y>
      <z>90.33732</z>
    </Vector3>
    <Vector3>
      <x>342.0709</x>
      <y>88.79994</y>
      <z>90.3694839</z>
    </Vector3>
    <Vector3>
      <x>340.460632</x>
      <y>88.76752</y>
      <z>90.41228</z>
    </Vector3>
    <Vector3>
      <x>338.386261</x>
      <y>88.7006454</y>
      <z>90.47868</z>
    </Vector3>
    <Vector3>
      <x>336.97818</x>
      <y>88.7075</y>
      <z>90.50555</z>
    </Vector3>
    <Vector3>
      <x>335.93692</x>
      <y>88.7260742</y>
      <z>90.51949</z>
    </Vector3>
    <Vector3>
      <x>335.3597</x>
      <y>88.75906</y>
      <z>90.51744</z>
    </Vector3>
    <Vector3>
      <x>334.804657</x>
      <y>88.771965</y>
      <z>90.52286</z>
    </Vector3>
  </_frameRot>
</GhostList>